pagebuilder/__init__.py
pagebuilder/component_interface.py
pagebuilder/example.py
pagebuilder-0.0.2.dist-info/LICENSE
pagebuilder-0.0.2.dist-info/METADATA
pagebuilder-0.0.2.dist-info/WHEEL
pagebuilder-0.0.2.dist-info/top_level.txt
pagebuilder-0.0.2.dist-info/RECORD
