Metadata-Version: 2.1
Name: pagebuilder
Version: 0.0.2
Summary: Python UI for Web Apps
Author-email: Zain Hoda <zain@pycob.com>
Project-URL: Homepage, https://github.com/pycob/pagebuilder
Project-URL: Bug Tracker, https://github.com/pycob/pagebuilder/issues
Classifier: Programming Language :: Python :: 3
Classifier: License :: OSI Approved :: MIT License
Classifier: Operating System :: OS Independent
Requires-Python: >=3.7
License-File: LICENSE
